confpoint/__init__.py
confpoint/image_tag.py
confpoint/shareup.py
confpoint/utils.py
confpoint/version.py
confpoint/downloader/__init__.py
confpoint/downloader/__main__.py
confpoint/downloader/onedownloader.py
confpoint/publisher/__init__.py
confpoint/publisher/__main__.py
confpoint/publisher/push.py
confpoint/uploader/__init__.py
confpoint/uploader/__main__.py
confpoint/uploader/oneloader.py
confpoint-1.2.1.dist-info/METADATA
confpoint-1.2.1.dist-info/WHEEL
confpoint-1.2.1.dist-info/entry_points.txt
confpoint-1.2.1.dist-info/top_level.txt
confpoint-1.2.1.dist-info/RECORD
