Metadata-Version: 2.1
Name: confpoint
Version: 1.2.1
Summary: Module for uploading MD file to the Confluence. Also alowed to uploading/downloading files to the SharePoint.
Home-page: https://github.com/Mcublog/confpoint
Author: Viacheslav
Author-email: viacheslav@mcublog.xyz
Classifier: Programming Language :: Python :: 3
Classifier: License :: OSI Approved :: MIT License
Classifier: Operating System :: OS Independent
Requires-Python: >=3.7
Requires-Dist: markdown==3.3.6
Requires-Dist: atlassian-python-api==3.20.1
Requires-Dist: shareplum==0.5.1
Requires-Dist: colorama==0.4.4
Requires-Dist: scanf==1.5.2
